LICENSE
MANIFEST.in
README.md
requirements.txt
setup.py
SemTorch.egg-info/PKG-INFO
SemTorch.egg-info/SOURCES.txt
SemTorch.egg-info/dependency_links.txt
SemTorch.egg-info/requires.txt
SemTorch.egg-info/top_level.txt
semtorch/__init__.py
semtorch/architectures_config.json
semtorch/learner.py
semtorch/models/__init__.py
semtorch/models/archs/__init__.py
semtorch/models/archs/deeplabv3_plus.py
semtorch/models/archs/hrnet_seg.py
semtorch/models/archs/mask_rcnn.py
semtorch/models/archs/segbase.py
semtorch/models/archs/tiramisu.py
semtorch/models/archs/u2net.py
semtorch/models/archs/backbones/__init__.py
semtorch/models/archs/backbones/build.py
semtorch/models/archs/backbones/hrnet.py
semtorch/models/archs/backbones/mobilenet.py
semtorch/models/archs/backbones/registry.py
semtorch/models/archs/backbones/resnet.py
semtorch/models/archs/backbones/xception.py
semtorch/models/config/__init__.py
semtorch/models/config/config.py
semtorch/models/config/settings.py
semtorch/models/modules/__init__.py
semtorch/models/modules/basic.py
semtorch/models/modules/batch_norm.py
semtorch/models/modules/bn_helper.py
semtorch/models/modules/module.py
semtorch/models/utils/__init__.py
semtorch/models/utils/distributed.py
semtorch/models/utils/download.py
semtorch/models/utils/filesystem.py
semtorch/models/utils/registry.py
semtorch/utils/__init__.py
semtorch/utils/mask_rcnn_visualize.py
semtorch/utils/metrics.py