Metadata-Version: 2.1
Name: SemTorch
Version: 0.1.1
Summary: Deep Leaarning segmentation architectures for PyTorch and FastAI
Home-page: https://github.com/WaterKnight1998/SemTorch
Author: David Lacalle Castillo
Author-email: dvdlacallecastillo@gmail.com
Maintainer: David Lacalle Castillo
Maintainer-email: dvdlacallecastillo@gmail.com
License: Apache License Version 2.0
Keywords: instance semantic segmentation pytorch fastai fastai2 fastaiv2 saliend object detection
Platform: UNKNOWN
Classifier: Development Status :: 3 - Alpha
Classifier: Intended Audience :: Science/Research
Classifier: Intended Audience :: Developers
Classifier: Topic :: Scientific/Engineering :: Image Recognition
Classifier: Topic :: Scientific/Engineering :: Artificial Intelligence
Classifier: License :: OSI Approved :: Apache Software License
Classifier: Programming Language :: Python :: 3.6
Classifier: Programming Language :: Python :: 3.7
Classifier: Programming Language :: Python :: 3.8
